{"color": {"white": {"t": {"w": 100, "y": 900, "h": 100, "x": 3755}, "w": 220, "y": 660, "h": 220, "x": 2690}, "yellow": {"t": {"w": 100, "y": 200, "h": 100, "x": 3755}, "w": 220, "y": 440, "h": 220, "x": 2690}, "green": {"t": {"w": 100, "y": 800, "h": 100, "x": 3655}, "w": 220, "y": 0, "h": 220, "x": 2690}, "brown": {"t": {"w": 100, "y": 900, "h": 100, "x": 3655}, "w": 220, "y": 220, "h": 220, "x": 2690}}, "head": {"top": {"t": {"w": 100, "y": 300, "h": 100, "x": 3755}, "w": 325, "y": 330, "h": 330, "x": 1870}, "tinfoil": {"t": {"w": 100, "y": 0, "h": 100, "x": 3555}, "w": 325, "y": 0, "h": 330, "x": 1220}, "maga": {"t": {"w": 100, "y": 100, "h": 100, "x": 3755}, "w": 325, "y": 0, "h": 330, "x": 1870}, "morion": {"t": {"w": 100, "y": 200, "h": 100, "x": 3555}, "w": 325, "y": 330, "h": 330, "x": 1220}, "nazi": {"t": {"w": 100, "y": 600, "h": 100, "x": 3755}, "w": 325, "y": 660, "h": 330, "x": 1870}, "tricornio": {"t": {"w": 100, "y": 0, "h": 100, "x": 3655}, "w": 325, "y": 0, "h": 330, "x": 1545}, "turban": {"t": {"w": 100, "y": 200, "h": 100, "x": 3655}, "w": 325, "y": 660, "h": 330, "x": 1545}, "pink_hair": {"t": {"w": 100, "y": 200, "h": 100, "x": 3855}, "w": 325, "y": 330, "h": 330, "x": 2195}, "commie": {"t": {"w": 100, "y": 100, "h": 100, "x": 3655}, "w": 325, "y": 330, "h": 330, "x": 1545}, "sideburns": {"t": {"w": 100, "y": 700, "h": 100, "x": 3555}, "w": 325, "y": 660, "h": 330, "x": 1220}, "montera": {"t": {"w": 100, "y": 700, "h": 100, "x": 3755}, "w": 325, "y": 0, "h": 330, "x": 2195}}, "neck": {"prolife": {"t": {"w": 100, "y": 400, "h": 100, "x": 3555}, "w": 170, "y": 0, "h": 200, "x": 2520}, "cross": {"t": {"w": 100, "y": 500, "h": 100, "x": 3655}, "w": 170, "y": 400, "h": 200, "x": 2520}, "prochoice": {"t": {"w": 100, "y": 600, "h": 100, "x": 3555}, "w": 170, "y": 200, "h": 200, "x": 2520}, "keffiyeh": {"t": {"w": 100, "y": 500, "h": 100, "x": 3755}, "w": 170, "y": 600, "h": 200, "x": 2520}}, "bracelets": {"spain": {"t": {"w": 100, "y": 500, "h": 100, "x": 3555}, "w": 80, "y": 0, "h": 100, "x": 3260}, "lgbt": {"t": {"w": 100, "y": 800, "h": 100, "x": 3755}, "w": 80, "y": 100, "h": 100, "x": 3260}}, "hand": {"dildo": {"t": {"w": 100, "y": 300, "h": 100, "x": 3555}, "w": 150, "y": 0, "h": 220, "x": 3405}, "gun": {"t": {"w": 100, "y": 800, "h": 100, "x": 3555}, "w": 150, "y": 220, "h": 220, "x": 3405}, "flute": {"t": {"w": 100, "y": 400, "h": 100, "x": 3755}, "w": 150, "y": 440, "h": 220, "x": 3405}}, "strawman": {"w": 1000, "y": 0, "h": 1000, "x": 0}, "badges": {"2030": {"t": {"w": 100, "y": 700, "h": 100, "x": 3655}, "w": 65, "y": 195, "h": 65, "x": 3340}, "yunque": {"t": {"w": 100, "y": 100, "h": 100, "x": 3855}, "w": 65, "y": 260, "h": 65, "x": 3340}, "illuminati": {"t": {"w": 100, "y": 100, "h": 100, "x": 3555}, "w": 65, "y": 0, "h": 65, "x": 3340}, "red_triangle": {"t": {"w": 100, "y": 300, "h": 100, "x": 3655}, "w": 65, "y": 65, "h": 65, "x": 3340}, "male": {"t": {"w": 100, "y": 600, "h": 100, "x": 3655}, "w": 65, "y": 130, "h": 65, "x": 3340}}, "chest": {"blue_shirt": {"t": {"w": 100, "y": 0, "h": 100, "x": 3755}, "w": 350, "y": 0, "h": 315, "x": 2910}, "lumberjack": {"t": {"w": 100, "y": 0, "h": 100, "x": 3855}, "w": 350, "y": 315, "h": 315, "x": 2910}}, "glasses": {"monocle": {"t": {"w": 100, "y": 900, "h": 100, "x": 3555}, "w": 220, "y": 0, "h": 220, "x": 1000}, "nose": {"t": {"w": 100, "y": 400, "h": 100, "x": 3655}, "w": 220, "y": 220, "h": 220, "x": 1000}}}